odoo9_addon_stock_valuation_account_manual_adjustment-9.0.1.0.0-py2.7-nspkg.pth
odoo9_addon_stock_valuation_account_manual_adjustment-9.0.1.0.0.dist-info/DESCRIPTION.rst
odoo9_addon_stock_valuation_account_manual_adjustment-9.0.1.0.0.dist-info/METADATA
odoo9_addon_stock_valuation_account_manual_adjustment-9.0.1.0.0.dist-info/RECORD
odoo9_addon_stock_valuation_account_manual_adjustment-9.0.1.0.0.dist-info/WHEEL
odoo9_addon_stock_valuation_account_manual_adjustment-9.0.1.0.0.dist-info/metadata.json
odoo9_addon_stock_valuation_account_manual_adjustment-9.0.1.0.0.dist-info/namespace_packages.txt
odoo9_addon_stock_valuation_account_manual_adjustment-9.0.1.0.0.dist-info/top_level.txt
odoo_addons/stock_valuation_account_manual_adjustment/README.rst
odoo_addons/stock_valuation_account_manual_adjustment/__init__.py
odoo_addons/stock_valuation_account_manual_adjustment/__openerp__.py
odoo_addons/stock_valuation_account_manual_adjustment/init_hook.py
odoo_addons/stock_valuation_account_manual_adjustment/data/stock_valuation_account_manual_adjustment_data.xml
odoo_addons/stock_valuation_account_manual_adjustment/i18n/am.po
odoo_addons/stock_valuation_account_manual_adjustment/i18n/ar.po
odoo_addons/stock_valuation_account_manual_adjustment/i18n/bg.po
odoo_addons/stock_valuation_account_manual_adjustment/i18n/bs.po
odoo_addons/stock_valuation_account_manual_adjustment/i18n/ca.po
odoo_addons/stock_valuation_account_manual_adjustment/i18n/ca_ES.po
odoo_addons/stock_valuation_account_manual_adjustment/i18n/cs.po
odoo_addons/stock_valuation_account_manual_adjustment/i18n/da.po
odoo_addons/stock_valuation_account_manual_adjustment/i18n/de.po
odoo_addons/stock_valuation_account_manual_adjustment/i18n/el_GR.po
odoo_addons/stock_valuation_account_manual_adjustment/i18n/en_AU.po
odoo_addons/stock_valuation_account_manual_adjustment/i18n/en_GB.po
odoo_addons/stock_valuation_account_manual_adjustment/i18n/es.po
odoo_addons/stock_valuation_account_manual_adjustment/i18n/es_AR.po
odoo_addons/stock_valuation_account_manual_adjustment/i18n/es_CL.po
odoo_addons/stock_valuation_account_manual_adjustment/i18n/es_CO.po
odoo_addons/stock_valuation_account_manual_adjustment/i18n/es_CR.po
odoo_addons/stock_valuation_account_manual_adjustment/i18n/es_DO.po
odoo_addons/stock_valuation_account_manual_adjustment/i18n/es_EC.po
odoo_addons/stock_valuation_account_manual_adjustment/i18n/es_ES.po
odoo_addons/stock_valuation_account_manual_adjustment/i18n/es_MX.po
odoo_addons/stock_valuation_account_manual_adjustment/i18n/es_PE.po
