Metadata-Version: 2.0
Name: odoo9-addon-stock-valuation-account-manual-adjustment
Version: 9.0.1.0.0
Summary: Shows in the product inventory stock value and the accounting value and allows to reconcile them
Home-page: https://github.com/OCA/stock-logistics-warehouse
Author: Eficent, Odoo Community Association (OCA)
Author-email: support@odoo-community.org
License: AGPL-3
Platform: UNKNOWN
Classifier: Programming Language :: Python :: 2.7
Classifier: Framework :: Odoo
Classifier: License :: OSI Approved :: GNU Affero General Public License v3
Requires-Dist: odoo (<9.1a,>=9.0a)
Requires-Dist: odoo9-addon-stock-inventory-revaluation
